bacnet_mcp/__init__.py
bacnet_mcp/cli.py
bacnet_mcp/server.py
bacnet_mcp/settings.py
bacnet_mcp/utils.py
bacnet_mcp-0.2.7.dist-info/METADATA
bacnet_mcp-0.2.7.dist-info/WHEEL
bacnet_mcp-0.2.7.dist-info/entry_points.txt
bacnet_mcp-0.2.7.dist-info/licenses/LICENSE
bacnet_mcp-0.2.7.dist-info/RECORD
