Metadata-Version: 2.4
Name: bacnet-mcp
Version: 0.2.7
Summary: A Model Context Protocol (MCP) server for BACnet.
License-File: LICENSE
Requires-Python: >=3.13
Requires-Dist: bacpypes3>=0.0.102
Requires-Dist: fastmcp>=2.11.0
Requires-Dist: pydantic-settings>=2.10.0
Requires-Dist: typer>=0.16.0
